[
    {"label": "Front-end", 
        "stack": [
            {"value": "React.js", "icon": "/assets/stacks/react.svg"},
            {"value": "HTML5", "icon": "/assets/stacks/html5.svg"},
            {"value": "CSS 3", "icon": "/assets/stacks/css3.svg"},
            {"value": "Vite.js", "icon": "/assets/stacks/vitejs.svg"},
            {"value": "Figma", "icon": "/assets/stacks/figma.svg"},
            {"value": "JavaScript", "icon": "/assets/stacks/js.svg"}
        ]
    },
    {"label": "Back-end", 
        "stack": [
            {"value": "Node.js", "icon": "/assets/stacks/nodejs.svg"},
            {"value": "Java", "icon": "/assets/stacks/java.svg"},
            {"value": "PHP", "icon": "/assets/stacks/php.svg"}
        ]
    },
    {"label": "Database", 
        "stack": [
            {"value": "MySQL", "icon": "/assets/stacks/mysql.svg"},      
            {"value": "Firebase", "icon": "/assets/stacks/firebase.svg"},
            {"value": "MS SQL", "icon": "/assets/stacks/mssql.svg"}    
        ]
    },
    {"label": "Version Control", 
        "stack": [
            {"value": "Git", "icon": "/assets/stacks/git.svg"},
            {"value": "GitHub", "icon": "/assets/stacks/github.svg"}
        ]
    },
    {"label": "Deployment & Hosting", 
        "stack": [
            {"value": "Vercel", "icon": "/assets/stacks/vercel.svg"},
            {"value": "Infinity Free", "icon": "/assets/stacks/infinityFree.svg"}
        ]
    },
    {"label": "Mobile Development", 
        "stack": [
            {"value": "Android", "icon": "/assets/stacks/android.svg "}
        ]
    }
]